flask_seasurf.py
Flask_SeaSurf-2.0.0.dist-info/LICENSE
Flask_SeaSurf-2.0.0.dist-info/METADATA
Flask_SeaSurf-2.0.0.dist-info/WHEEL
Flask_SeaSurf-2.0.0.dist-info/top_level.txt
Flask_SeaSurf-2.0.0.dist-info/RECORD
